.DS_Store
pytrendex/__init__.py
pytrendex/core.py
pytrendex-5.0.0.dist-info/LICENSE
pytrendex-5.0.0.dist-info/METADATA
pytrendex-5.0.0.dist-info/WHEEL
pytrendex-5.0.0.dist-info/top_level.txt
pytrendex-5.0.0.dist-info/RECORD
