Metadata-Version: 2.1
Name: pytrendex
Version: 5.0.0
Summary: Tool To Create Google Trends Index From Keywords
Home-page: https://github.com/lucashusted/pytrendex
Author: Lucas Husted
Author-email: lucas.f.husted@columbia.edu
License: GNU
Platform: UNKNOWN
Classifier: Development Status :: 3 - Alpha
Classifier: Intended Audience :: Developers
Classifier: Programming Language :: Python :: 3.3
Classifier: Programming Language :: Python :: 3.4
Classifier: Programming Language :: Python :: 3.5
Classifier: Programming Language :: Python :: 3.6
Classifier: Programming Language :: Python :: 3.7
Requires-Python: >=3
Requires-Dist: pytrends
Requires-Dist: requests
Requires-Dist: numpy
Requires-Dist: statsmodels
Requires-Dist: pandas (>=0.25)
Requires-Dist: lxml
Requires-Dist: matplotlib
